{
  "version": "0.17.0",
  "tag": "v0.17.0",
  "channel": "alpha",
  "mandatory": false,
  "minSupportedVersion": "0.1.0",
  "releasedAt": "2026-06-20",
  "windows": {
    "url": "https://github.com/CasperW04/reptile-shop-releases/releases/download/v0.17.0/ReptileShop-Windows-v0.17.0.zip",
    "sizeBytes": 44758129,
    "sha256": "6c91ce23bebf1c72471032ffee5caf04ef260c63d274d4924a6a3f0735ec52e4"
  },
  "notesUrl": "https://github.com/CasperW04/reptile-shop-releases/blob/main/CHANGELOG.md",
  "notes": "Alpha v0.17.0 - Sparkonto i banken: satt in pengar och tjana 1 procent ranta per dygn. Satt in och ta ut via Bank-appen."
}