{
  "version": "0.96.0",
  "tag": "v0.96.0",
  "channel": "alpha",
  "mandatory": false,
  "minSupportedVersion": "0.1.0",
  "releasedAt": "2026-06-20",
  "windows": {
    "url": "https://github.com/CasperW04/reptile-shop-releases/releases/download/v0.96.0/ReptileShop-Windows-v0.96.0.zip",
    "sizeBytes": 44902489,
    "sha256": "c32b757e19a06391d2a38a56dd527ede6d6cf26ebe47667a65f57309fc2360be"
  },
  "notesUrl": "https://github.com/CasperW04/reptile-shop-releases/blob/main/CHANGELOG.md",
  "notes": "Alpha v0.96.0 - Breeding Lines: mark djur med projekt/linjenamn och se antal per linje; avkomma arver faderns linje vid klackning. Builder C."
}